macalc/__init__.py
macalc/calculator.py
macalc_gi/__init__.py
macalc_gi/calculator.py
macalc_gi/statgi.py
mycalc_gi-0.0.2.dist-info/LICENSE
mycalc_gi-0.0.2.dist-info/METADATA
mycalc_gi-0.0.2.dist-info/WHEEL
mycalc_gi-0.0.2.dist-info/top_level.txt
mycalc_gi-0.0.2.dist-info/RECORD
