Metadata-Version: 2.1
Name: mycalc-gi
Version: 0.0.2
Summary: nice calculator
Home-page: https://github.com/GitaeBak/unv_oss
Download-URL: https://github.com/GitaeBak/unv_oss
Author: gitaebak
Classifier: Programming Language :: Python :: 3
License-File: LICENSE
Requires-Dist: pandas
Requires-Dist: numpy
Requires-Dist: matplotlib
